diff_classifier/__init__.py
diff_classifier/aws.py
diff_classifier/due.py
diff_classifier/features.py
diff_classifier/heatmaps.py
diff_classifier/imagej.py
diff_classifier/knotlets.py
diff_classifier/msd.py
diff_classifier/pca.py
diff_classifier/utils.py
diff_classifier/version.py
diff_classifier/data/test.xml
diff_classifier/data/test2.xml
diff_classifier/data/trackmate_template.py
diff_classifier/data/trackmate_template2.py
diff_classifier/data/trackmate_template3.py
diff_classifier-0.1.dev0.dist-info/LICENSE
diff_classifier-0.1.dev0.dist-info/METADATA
diff_classifier-0.1.dev0.dist-info/WHEEL
diff_classifier-0.1.dev0.dist-info/top_level.txt
diff_classifier-0.1.dev0.dist-info/RECORD
