Metadata-Version: 2.1
Name: diff-classifier
Version: 0.1.dev0
Summary: 
Home-page: https://github.com/ccurtis7/diff_classifier
Author: Chad Curtis
Author-email: ccurtis7@uw.edu
Maintainer: Chad Curtis
Maintainer-email: ccurtis7@uw.edu
License: MIT
Platform: OS Independent
Classifier: Development Status :: 3 - Alpha
Classifier: Environment :: Console
Classifier: License :: OSI Approved :: BSD License
Classifier: Operating System :: OS Independent
Classifier: Programming Language :: Python
Requires-Dist: coverage (==4.5.2)
Requires-Dist: coveralls
Requires-Dist: pytest (==4.1.0)
Requires-Dist: numpy
Requires-Dist: scipy
Requires-Dist: pandas
Requires-Dist: scikit-image
Requires-Dist: sklearn
Requires-Dist: boto3
Requires-Dist: shapely
Requires-Dist: numpydoc
Requires-Dist: ipywidgets
Requires-Dist: seaborn
Requires-Dist: Shapely
Requires-Dist: fijibin
